[{
    "id": "001",
    "sName": "Juan Jose Salvador Cabañas",
    "className": "4to A",
    "dateStart": "2019-02-17T14:22:18Z",
    "timeWork": "10:30",
    "status": "Confirmado"
  },
  {
    "id": "002",
    "sName": "Paulina Castro Ayala",
    "className": "5to A",
    "dateStart": "2019-02-19T14:22:18Z",
    "timeWork": "10:30",
    "status": "Cancelado"
  },
  {
    "id": "003",
    "sName": "Rodrigo Gonzales Sebastian",
    "className": "4to B",
    "dateStart": "2019-02-22T14:22:18Z",
    "timeWork": "10:30",
    "status": "Realizado"
  }
]
